vader/__init__.py
vader/pretrained/logistic.joblib
vader/pretrained/nb.joblib
vader/pretrained/nn.joblib
vader/train/__init__.py
vader-0.0.2.dist-info/LICENSE
vader-0.0.2.dist-info/METADATA
vader-0.0.2.dist-info/WHEEL
vader-0.0.2.dist-info/top_level.txt
vader-0.0.2.dist-info/RECORD
